[
  {
    "chartdata": {
      "grafik": [
        {
          "tingkat": "Banten",
          "name": "Garis Kemiskinan",
          "tahun": [
            {
              "2013": 288733,
              "2014": 315819,
              "2015": 356436,
              "2016": 373365
            }
          ]
        },
        {
          "tingkat": "Indonesia",
          "name": "Garis Kemiskinan",
          "tahun": [
            {
              "2013": 292951,
              "2014": 312328,
              "2015": 344809,
              "2016": 361990
            }
          ]
        },
        {
          "tingkat": "Banten",
          "name": "Penduduk Miskin",
          "tahun": [
            {
              "2013": 677508,
              "2014": 649188,
              "2015": 690668,
              "2016": 657740
            }
          ]
        },
        {
          "tingkat": "Indonesia",
          "name": "Penduduk Miskin",
          "tahun": [
            {
              "2013": 28606685,
              "2014": 27727778,
              "2015": 28513570,
              "2016": 27764320
            }
          ]
        },
        {
          "tingkat": "Banten",
          "name": "Penduduk Tidak Miskin",
          "tahun": [
            {
              "2013": 10817843,
              "2014": 11126494,
              "2015": 11325308,
              "2016": 11606265
            }
          ]
        },
        {
          "tingkat": "Indonesia",
          "name": "Penduduk Tidak Miskin",
          "tahun": [
            {
              "2013": 221027765,
              "2014": 225337016,
              "2015": 227719363,
              "2016": 231733374
            }
          ]
        }
      ]
    }
  }
]
